{
    "stocks": [
        { "symbol": "2330", "name": "台積電", "market": "tw", "close": 2260.0, "ma60": 1952.15, "rsi": 66.9, "trend_score": 100, "vol_ratio": 0.73, "signal": "Strong Buy", "sector": "台股權值", "tactic": "全球 AI 心臟。", "plan": { "entry": 2250, "sl": 1950, "tp": 2800 } },
        { "symbol": "2317", "name": "鴻海", "market": "tw", "close": 230.0, "ma60": 215.9, "rsi": 71.5, "trend_score": 100, "vol_ratio": 1.11, "signal": "Strong Buy", "sector": "AI 基建", "tactic": "GB200 霸主。", "plan": { "entry": 225, "sl": 215, "tp": 280 } },
        { "symbol": "2313", "name": "華通", "market": "tw", "close": 128.5, "ma60": 110.2, "rsi": 78.5, "trend_score": 95, "vol_ratio": 2.4, "signal": "Strong Buy", "sector": "太空經濟", "tactic": "衛星通訊板龍頭。", "plan": { "entry": 125, "sl": 110, "tp": 160 } },
        { "symbol": "NVDA", "name": "NVIDIA", "market": "us", "close": 1250.0, "ma60": 1180.5, "rsi": 68.2, "trend_score": 100, "vol_ratio": 1.2, "signal": "Strong Buy", "sector": "AI 晶片", "tactic": "算力王者。", "plan": { "entry": 1200, "sl": 1150, "tp": 1500 } },
        { "symbol": "TSM", "name": "TSM ADR", "market": "us", "close": 195.0, "ma60": 182.6, "rsi": 62.1, "trend_score": 95, "vol_ratio": 1.1, "signal": "Strong Buy", "sector": "半導體", "tactic": "ADR 溢價觀察。", "plan": { "entry": 190, "sl": 180, "tp": 230 } }
    ],
    "adr_premium": 12.68,
    "suggested_cash": 70
}