{
  "台股加權": {
    "close": 41650.12,
    "change": 0.67,
    "signal": "Buy"
  },
  "美金/台幣": {
    "close": 31.5,
    "change": -0.0,
    "signal": "Wait"
  },
  "10年美債(殖利率)": {
    "close": 4.48,
    "change": 0.38,
    "signal": "Buy"
  },
  "費城半導體": {
    "close": 12017.98,
    "change": 2.57,
    "signal": "Buy"
  },
  "美股標普": {
    "close": 7444.25,
    "change": 0.58,
    "signal": "Buy"
  },
  "那斯達克": {
    "close": 26402.34,
    "change": 1.2,
    "signal": "Buy"
  },
  "US VIX (恐慌)": {
    "close": 17.87,
    "change": -0.67,
    "signal": "Wait"
  },
  "ADR 溢價": {
    "close": 12.2,
    "advice": "溢價"
  },
  "adr_premium": {
    "close": 12.2,
    "advice": "溢價"
  },
  "fear_greed": {
    "value": 67,
    "sentiment": "Greed"
  },
  "suggested_cash": 30
}