[{"time": "2025-11-21", "open": 477.41, "high": 477.83, "low": 467.2, "close": 471.04}, {"time": "2025-11-24", "open": 473.92, "high": 475.81, "low": 466.95, "close": 472.92}, {"time": "2025-11-25", "open": 472.99, "high": 478.06, "low": 463.83, "close": 475.9}, {"time": "2025-11-26", "open": 485.2, "high": 487.2, "low": 480.1, "close": 484.39}, {"time": "2025-11-28", "open": 486.49, "high": 491.51, "low": 485.54, "close": 490.89}, {"time": "2025-12-01", "open": 487.33, "high": 488.74, "low": 483.55, "close": 485.63}, {"time": "2025-12-02", "open": 485.61, "high": 492.38, "low": 485.21, "close": 488.88}, {"time": "2025-12-03", "open": 475.24, "high": 483.14, "low": 474.12, "close": 476.64}, {"time": "2025-12-04", "open": 478.67, "high": 480.22, "low": 475.4, "close": 479.74}, {"time": "2025-12-05", "open": 481.42, "high": 482.3, "low": 477.79, "close": 482.06}, {"time": "2025-12-08", "open": 483.79, "high": 491.18, "low": 483.28, "close": 489.9}, {"time": "2025-12-09", "open": 487.99, "high": 491.0, "low": 487.39, "close": 490.9}, {"time": "2025-12-10", "open": 482.93, "high": 483.15, "low": 474.0, "close": 477.47}, {"time": "2025-12-11", "open": 475.54, "high": 484.92, "low": 474.78, "close": 482.37}, {"time": "2025-12-12", "open": 478.73, "high": 481.35, "low": 475.26, "close": 477.44}, {"time": "2025-12-15", "open": 479.01, "high": 479.63, "low": 471.44, "close": 473.74}, {"time": "2025-12-16", "open": 470.84, "high": 476.8, "low": 469.81, "close": 475.31}, {"time": "2025-12-17", "open": 475.82, "high": 478.91, "low": 473.92, "close": 475.04}, {"time": "2025-12-18", "open": 477.1, "high": 488.49, "low": 476.8, "close": 482.88}, {"time": "2025-12-19", "open": 486.25, "high": 486.74, "low": 481.39, "close": 484.81}, {"time": "2025-12-22", "open": 485.01, "high": 487.62, "low": 481.59, "close": 483.82}, {"time": "2025-12-23", "open": 483.88, "high": 486.72, "low": 483.64, "close": 485.74}, {"time": "2025-12-24", "open": 484.57, "high": 488.05, "low": 483.73, "close": 486.91}, {"time": "2025-12-26", "open": 485.6, "high": 487.01, "low": 484.85, "close": 486.6}, {"time": "2025-12-29", "open": 483.76, "high": 487.24, "low": 483.08, "close": 485.99}, {"time": "2025-12-30", "open": 484.82, "high": 488.56, "low": 484.39, "close": 486.37}, {"time": "2025-12-31", "open": 486.73, "high": 487.03, "low": 482.2, "close": 482.52}, {"time": "2026-01-02", "open": 483.29, "high": 483.56, "low": 469.09, "close": 471.86}, {"time": "2026-01-05", "open": 472.98, "high": 474.99, "low": 468.43, "close": 471.77}, {"time": "2026-01-06", "open": 472.72, "high": 477.65, "low": 468.68, "close": 477.42}, {"time": "2026-01-07", "open": 478.67, "high": 488.58, "low": 476.86, "close": 482.37}, {"time": "2026-01-08", "open": 480.14, "high": 481.56, "low": 474.78, "close": 477.02}, {"time": "2026-01-09", "open": 472.98, "high": 478.73, "low": 471.12, "close": 478.19}, {"time": "2026-01-12", "open": 475.58, "high": 479.89, "low": 474.6, "close": 476.09}, {"time": "2026-01-13", "open": 473.6, "high": 474.7, "low": 464.89, "close": 469.6}, {"time": "2026-01-14", "open": 465.4, "high": 467.13, "low": 456.13, "close": 458.33}, {"time": "2026-01-15", "open": 463.06, "high": 463.19, "low": 454.86, "close": 455.62}, {"time": "2026-01-16", "open": 456.79, "high": 462.14, "low": 455.44, "close": 458.81}, {"time": "2026-01-20", "open": 450.19, "high": 455.76, "low": 448.26, "close": 453.48}, {"time": "2026-01-21", "open": 451.57, "high": 451.66, "low": 437.68, "close": 443.1}, {"time": "2026-01-22", "open": 446.6, "high": 451.81, "low": 443.69, "close": 450.11}, {"time": "2026-01-23", "open": 450.84, "high": 470.03, "low": 449.5, "close": 464.89}, {"time": "2026-01-26", "open": 464.25, "high": 473.17, "low": 460.95, "close": 469.21}, {"time": "2026-01-27", "open": 472.62, "high": 481.77, "low": 472.08, "close": 479.49}, {"time": "2026-01-28", "open": 482.11, "high": 482.64, "low": 476.91, "close": 480.53}, {"time": "2026-01-29", "open": 438.99, "high": 441.49, "low": 420.06, "close": 432.51}, {"time": "2026-01-30", "open": 438.17, "high": 438.6, "low": 425.48, "close": 429.31}, {"time": "2026-02-02", "open": 429.26, "high": 429.76, "low": 421.29, "close": 422.41}, {"time": "2026-02-03", "open": 421.05, "high": 421.09, "low": 407.63, "close": 410.27}, {"time": "2026-02-04", "open": 410.06, "high": 418.84, "low": 408.31, "close": 413.25}, {"time": "2026-02-05", "open": 406.51, "high": 407.37, "low": 391.43, "close": 392.77}, {"time": "2026-02-06", "open": 398.26, "high": 400.88, "low": 392.03, "close": 400.23}, {"time": "2026-02-09", "open": 403.93, "high": 413.95, "low": 399.96, "close": 412.66}, {"time": "2026-02-10", "open": 418.66, "high": 422.72, "low": 411.76, "close": 412.33}, {"time": "2026-02-11", "open": 415.23, "high": 415.51, "low": 400.1, "close": 403.45}, {"time": "2026-02-12", "open": 404.08, "high": 405.27, "low": 397.1, "close": 400.92}, {"time": "2026-02-13", "open": 403.53, "high": 404.62, "low": 397.14, "close": 400.41}, {"time": "2026-02-17", "open": 398.31, "high": 399.61, "low": 393.63, "close": 395.96}, {"time": "2026-02-18", "open": 397.22, "high": 401.64, "low": 395.42, "close": 398.69}, {"time": "2026-02-19", "open": 400.69, "high": 404.43, "low": 396.67, "close": 398.46}, {"time": "2026-02-20", "open": 396.11, "high": 400.12, "low": 395.16, "close": 397.23}, {"time": "2026-02-23", "open": 395.0, "high": 395.36, "low": 383.1, "close": 384.47}, {"time": "2026-02-24", "open": 384.14, "high": 389.36, "low": 381.71, "close": 389.0}, {"time": "2026-02-25", "open": 390.53, "high": 401.47, "low": 390.16, "close": 400.6}, {"time": "2026-02-26", "open": 404.71, "high": 407.49, "low": 398.74, "close": 401.72}, {"time": "2026-02-27", "open": 390.88, "high": 396.82, "low": 389.88, "close": 392.74}, {"time": "2026-03-02", "open": 392.86, "high": 401.19, "low": 390.63, "close": 398.55}, {"time": "2026-03-03", "open": 393.14, "high": 406.7, "low": 392.67, "close": 403.93}, {"time": "2026-03-04", "open": 401.27, "high": 411.03, "low": 400.31, "close": 405.2}, {"time": "2026-03-05", "open": 404.42, "high": 411.61, "low": 404.4, "close": 410.68}, {"time": "2026-03-06", "open": 409.2, "high": 413.05, "low": 408.51, "close": 408.96}, {"time": "2026-03-09", "open": 404.92, "high": 410.21, "low": 403.5, "close": 409.41}, {"time": "2026-03-10", "open": 410.03, "high": 410.2, "low": 402.93, "close": 405.76}, {"time": "2026-03-11", "open": 405.57, "high": 409.01, "low": 401.59, "close": 404.88}, {"time": "2026-03-12", "open": 404.63, "high": 406.12, "low": 401.71, "close": 401.86}, {"time": "2026-03-13", "open": 401.0, "high": 404.8, "low": 394.25, "close": 395.55}, {"time": "2026-03-16", "open": 398.07, "high": 400.63, "low": 394.79, "close": 399.95}, {"time": "2026-03-17", "open": 400.27, "high": 404.4, "low": 397.75, "close": 399.41}, {"time": "2026-03-18", "open": 397.13, "high": 398.0, "low": 391.0, "close": 391.79}, {"time": "2026-03-19", "open": 390.1, "high": 392.49, "low": 387.06, "close": 389.02}, {"time": "2026-03-20", "open": 386.79, "high": 387.0, "low": 380.12, "close": 381.87}, {"time": "2026-03-23", "open": 383.9, "high": 387.21, "low": 381.68, "close": 383.0}, {"time": "2026-03-24", "open": 382.36, "high": 382.47, "low": 371.85, "close": 372.74}, {"time": "2026-03-25", "open": 376.92, "high": 377.06, "low": 369.63, "close": 371.04}, {"time": "2026-03-26", "open": 370.82, "high": 374.72, "low": 365.19, "close": 365.97}, {"time": "2026-03-27", "open": 361.9, "high": 362.45, "low": 356.51, "close": 356.77}, {"time": "2026-03-30", "open": 361.9, "high": 365.36, "low": 356.28, "close": 358.96}, {"time": "2026-03-31", "open": 364.55, "high": 372.9, "low": 363.07, "close": 370.17}, {"time": "2026-04-01", "open": 373.49, "high": 373.99, "low": 368.2, "close": 369.37}, {"time": "2026-04-02", "open": 367.21, "high": 373.64, "low": 364.15, "close": 373.46}, {"time": "2026-04-06", "open": 373.49, "high": 373.73, "low": 369.5, "close": 372.88}, {"time": "2026-04-07", "open": 370.34, "high": 372.45, "low": 366.56, "close": 372.29}, {"time": "2026-04-08", "open": 384.98, "high": 385.0, "low": 371.41, "close": 374.33}, {"time": "2026-04-09", "open": 372.5, "high": 373.5, "low": 367.05, "close": 373.07}, {"time": "2026-04-10", "open": 372.98, "high": 375.64, "low": 370.03, "close": 370.87}, {"time": "2026-04-13", "open": 373.61, "high": 384.54, "low": 371.02, "close": 384.37}, {"time": "2026-04-14", "open": 387.92, "high": 394.69, "low": 386.52, "close": 393.11}, {"time": "2026-04-15", "open": 398.0, "high": 414.37, "low": 396.73, "close": 411.22}, {"time": "2026-04-16", "open": 419.86, "high": 420.82, "low": 412.14, "close": 420.26}, {"time": "2026-04-17", "open": 424.82, "high": 431.58, "low": 420.69, "close": 422.79}, {"time": "2026-04-20", "open": 421.15, "high": 423.33, "low": 416.3, "close": 418.07}, {"time": "2026-04-21", "open": 420.24, "high": 427.18, "low": 417.2, "close": 424.16}, {"time": "2026-04-22", "open": 426.19, "high": 433.7, "low": 423.67, "close": 432.92}, {"time": "2026-04-23", "open": 419.89, "high": 423.66, "low": 411.41, "close": 415.75}, {"time": "2026-04-24", "open": 416.97, "high": 424.95, "low": 415.8, "close": 424.62}, {"time": "2026-04-27", "open": 422.38, "high": 427.11, "low": 417.07, "close": 424.82}, {"time": "2026-04-28", "open": 424.57, "high": 429.92, "low": 421.9, "close": 429.25}, {"time": "2026-04-29", "open": 424.58, "high": 426.82, "low": 420.29, "close": 424.46}, {"time": "2026-04-30", "open": 410.81, "high": 414.42, "low": 398.01, "close": 407.78}, {"time": "2026-05-01", "open": 412.8, "high": 417.11, "low": 410.44, "close": 414.44}, {"time": "2026-05-04", "open": 411.54, "high": 420.78, "low": 410.8, "close": 413.62}, {"time": "2026-05-05", "open": 415.32, "high": 416.78, "low": 408.8, "close": 411.38}, {"time": "2026-05-06", "open": 408.0, "high": 418.42, "low": 405.11, "close": 413.96}, {"time": "2026-05-07", "open": 420.11, "high": 427.98, "low": 418.76, "close": 420.77}, {"time": "2026-05-08", "open": 417.39, "high": 418.63, "low": 414.0, "close": 415.12}, {"time": "2026-05-11", "open": 407.87, "high": 412.69, "low": 405.5, "close": 412.66}, {"time": "2026-05-12", "open": 414.48, "high": 415.5, "low": 406.64, "close": 407.77}, {"time": "2026-05-13", "open": 403.2, "high": 406.31, "low": 401.03, "close": 405.21}, {"time": "2026-05-14", "open": 404.48, "high": 411.84, "low": 400.88, "close": 409.43}, {"time": "2026-05-15", "open": 414.41, "high": 417.2, "low": 412.92, "close": 416.74}]